{
  "app_name": "Bullhorn CRM",
  "app_slug": "bullhorn-crm",
  "search_term": "Find the official pricing page URL for Bullhorn CRM (bullhorn-crm.com). Only provide the exact URL to the pricing page, not a summary of pricing information.",
  "timestamp": 1744696233.8972366,
  "response_text": [
    "The official pricing page URL for Bullhorn CRM is: [https://www.bullhorn.com/pricing/](https://www.bullhorn.com/pricing/)\u30103:0\u2020source\u3011."
  ],
  "citations": [
    {
      "title": "Pricing - Bullhorn",
      "url": "https://www.bullhorn.com/pricing/"
    }
  ],
  "extracted_content": [
    {
      "url": "https://www.bullhorn.com/pricing/",
      "is_accessible": false,
      "content": null,
      "error": "Exception: HTTPSConnectionPool(host='r.jina.ai', port=443): Read timed out. (read timeout=15)"
    }
  ],
  "results_directory": "pricing_results\\bullhorn-crm\\20250415_015049"
}